{
  "$meta": {
    "source": "kemet-core/brand-kit (brand-tokens.json v2.0.0 + tokens.css)",
    "note": "Nomes de token do nilo preservados; valores reconciliados com o brand-kit Kemet. Ver RECONCILIACAO-KEMET.md."
  },
  "color": {
    "neutral": {
      "50":  { "value": "#FAF8F2", "type": "color", "kemet": "papyrus.50" },
      "100": { "value": "#E8E4DC", "type": "color", "kemet": "sand.100" },
      "200": { "value": "#DCD6C8", "type": "color", "kemet": "sand.200" },
      "300": { "value": "#C8C2B5", "type": "color", "kemet": "sand.300" },
      "400": { "value": "#8C8C8C", "type": "color", "kemet": "stone.400" },
      "500": { "value": "#6B6B6B", "type": "color", "kemet": "stone.500" },
      "600": { "value": "#4B4B4B", "type": "color", "kemet": "interpolado (sem par canônico)" },
      "700": { "value": "#2B2B2B", "type": "color", "kemet": "graphite.700" },
      "800": { "value": "#1F1F1F", "type": "color", "kemet": "graphite.800" },
      "900": { "value": "#141414", "type": "color", "kemet": "onyx.900" },
      "950": { "value": "#0A0A0A", "type": "color", "kemet": "onyx.950 / kemet.black" }
    },
    "royal": {
      "50":  { "value": "#F4ECFF", "type": "color" },
      "100": { "value": "#E5D2FF", "type": "color" },
      "200": { "value": "#CFAEFF", "type": "color" },
      "300": { "value": "#B884FF", "type": "color" },
      "400": { "value": "#9854E5", "type": "color" },
      "500": { "value": "#7B2CBF", "type": "color" },
      "600": { "value": "#65229F", "type": "color" },
      "700": { "value": "#4F1A7E", "type": "color" },
      "800": { "value": "#3A1359", "type": "color" },
      "900": { "value": "#240B36", "type": "color" }
    },
    "accent": {
      "50":  { "value": "#F4ECFF", "type": "color", "kemet": "royal.50" },
      "100": { "value": "#E5D2FF", "type": "color", "kemet": "royal.100" },
      "200": { "value": "#CFAEFF", "type": "color", "kemet": "royal.200" },
      "300": { "value": "#B884FF", "type": "color", "kemet": "royal.300" },
      "400": { "value": "#9854E5", "type": "color", "kemet": "royal.400" },
      "500": { "value": "#7B2CBF", "type": "color", "kemet": "royal.500" },
      "600": { "value": "#65229F", "type": "color", "kemet": "royal.600" },
      "700": { "value": "#4F1A7E", "type": "color", "kemet": "royal.700" },
      "800": { "value": "#3A1359", "type": "color", "kemet": "royal.800" },
      "900": { "value": "#240B36", "type": "color", "kemet": "royal.900" },
      "950": { "value": "#240B36", "type": "color", "kemet": "alias de royal.900 (Kemet não tem 950)" }
    },
    "olive": {
      "50":  { "value": "#F4F6E6", "type": "color" },
      "100": { "value": "#E6EBC7", "type": "color" },
      "200": { "value": "#D2DA9E", "type": "color" },
      "300": { "value": "#B8C56A", "type": "color" },
      "400": { "value": "#9DAD45", "type": "color" },
      "500": { "value": "#6E7A2E", "type": "color" },
      "600": { "value": "#5A6325", "type": "color" },
      "700": { "value": "#454C1C", "type": "color" },
      "800": { "value": "#2F3413", "type": "color" },
      "900": { "value": "#191C0A", "type": "color" }
    },
    "sun": {
      "50":  { "value": "#FFF1E6", "type": "color" },
      "100": { "value": "#FFD9BF", "type": "color" },
      "200": { "value": "#FFB888", "type": "color" },
      "300": { "value": "#FF9555", "type": "color" },
      "400": { "value": "#FA7A2C", "type": "color" },
      "500": { "value": "#F26419", "type": "color" },
      "600": { "value": "#CE5210", "type": "color" },
      "700": { "value": "#A23F09", "type": "color" },
      "800": { "value": "#742C05", "type": "color" },
      "900": { "value": "#3F1802", "type": "color" }
    },
    "semantic": {
      "success": { "value": "#2F8A4E", "type": "color" },
      "error":   { "value": "#C73838", "type": "color" },
      "warning": { "value": "#D4A018", "type": "color" },
      "info":    { "value": "#3B6CC9", "type": "color" }
    },
    "brand": {
      "olive": { "value": "#6E7A2E", "type": "color", "kemet": "olive.500" },
      "cream": { "value": "#FAF8F2", "type": "color", "kemet": "papyrus.50" }
    }
  },
  "typography": {
    "fontFamily": {
      "display": { "value": "\"Space Grotesk\", ui-sans-serif, system-ui, sans-serif", "type": "fontFamily" },
      "body":    { "value": "Inter, ui-sans-serif, system-ui, sans-serif",              "type": "fontFamily" },
      "mono":    { "value": "\"Nova Mono\", ui-monospace, \"JetBrains Mono\", Menlo, monospace", "type": "fontFamily" }
    },
    "fontSize": {
      "display-2xl": { "value": "72px", "type": "fontSize" },
      "display-xl":  { "value": "56px", "type": "fontSize" },
      "display-lg":  { "value": "44px", "type": "fontSize" },
      "heading-xl":  { "value": "36px", "type": "fontSize" },
      "heading-lg":  { "value": "28px", "type": "fontSize" },
      "heading-md":  { "value": "22px", "type": "fontSize" },
      "body-lg":     { "value": "18px", "type": "fontSize" },
      "body-md":     { "value": "16px", "type": "fontSize" },
      "body-sm":     { "value": "14px", "type": "fontSize" },
      "label-lg":    { "value": "13px", "type": "fontSize" },
      "label-sm":    { "value": "11px", "type": "fontSize" },
      "caption":     { "value": "12px", "type": "fontSize" }
    },
    "lineHeight": {
      "tight":   { "value": "1.05", "type": "lineHeight" },
      "snug":    { "value": "1.2",  "type": "lineHeight" },
      "normal":  { "value": "1.4",  "type": "lineHeight" },
      "relaxed": { "value": "1.6",  "type": "lineHeight" }
    },
    "letterSpacing": {
      "tighter": { "value": "-0.03em",  "type": "letterSpacing" },
      "tight":   { "value": "-0.015em", "type": "letterSpacing" },
      "normal":  { "value": "0",        "type": "letterSpacing" },
      "wide":    { "value": "0.04em",   "type": "letterSpacing" },
      "wider":   { "value": "0.12em",   "type": "letterSpacing" }
    },
    "fontWeight": {
      "regular":  { "value": "400", "type": "fontWeight" },
      "medium":   { "value": "500", "type": "fontWeight" },
      "semibold": { "value": "600", "type": "fontWeight" },
      "bold":     { "value": "700", "type": "fontWeight" }
    }
  },
  "spacing": {
    "1":  { "value": "4px",   "type": "spacing", "kemet": "spacing.1" },
    "2":  { "value": "8px",   "type": "spacing", "kemet": "spacing.2" },
    "3":  { "value": "12px",  "type": "spacing", "kemet": "spacing.3" },
    "4":  { "value": "16px",  "type": "spacing", "kemet": "spacing.4" },
    "5":  { "value": "20px",  "type": "spacing", "kemet": "fora da escala canônica" },
    "6":  { "value": "24px",  "type": "spacing", "kemet": "spacing.5" },
    "8":  { "value": "32px",  "type": "spacing", "kemet": "spacing.6" },
    "10": { "value": "40px",  "type": "spacing", "kemet": "spacing.7" },
    "12": { "value": "48px",  "type": "spacing", "kemet": "fora da escala canônica" },
    "14": { "value": "56px",  "type": "spacing", "kemet": "spacing.8" },
    "16": { "value": "64px",  "type": "spacing", "kemet": "fora da escala canônica" },
    "20": { "value": "80px",  "type": "spacing", "kemet": "spacing.9" },
    "24": { "value": "96px",  "type": "spacing", "kemet": "fora da escala canônica" },
    "30": { "value": "120px", "type": "spacing", "kemet": "spacing.10" },
    "32": { "value": "128px", "type": "spacing", "kemet": "fora da escala canônica" },
    "40": { "value": "160px", "type": "spacing", "kemet": "spacing.11" }
  },
  "borderRadius": {
    "sm":   { "value": "6px",    "type": "borderRadius", "kemet": "radius.sm" },
    "md":   { "value": "12px",   "type": "borderRadius", "kemet": "radius.md" },
    "lg":   { "value": "20px",   "type": "borderRadius", "kemet": "radius.lg" },
    "xl":   { "value": "28px",   "type": "borderRadius", "kemet": "radius.xl" },
    "2xl":  { "value": "28px",   "type": "borderRadius", "kemet": "alias de radius.xl" },
    "full": { "value": "9999px", "type": "borderRadius", "kemet": "radius.full" }
  },
  "shadow": {
    "sm":     { "value": "0 1px 2px rgba(10,10,10,0.06)",  "type": "boxShadow" },
    "md":     { "value": "0 8px 24px rgba(10,10,10,0.08)", "type": "boxShadow" },
    "lg":     { "value": "0 20px 48px rgba(10,10,10,0.12)","type": "boxShadow" },
    "accent": { "value": "0 0 60px rgba(123,44,191,0.45)", "type": "boxShadow", "kemet": "glow.royal" },
    "focus-ring": { "value": "0 0 0 3px rgba(123,44,191,0.32)", "type": "boxShadow" }
  },
  "motion": {
    "duration": {
      "fast":  { "value": "160ms", "type": "duration" },
      "base":  { "value": "240ms", "type": "duration" },
      "slow":  { "value": "420ms", "type": "duration" },
      "xslow": { "value": "720ms", "type": "duration" }
    },
    "easing": {
      "default": { "value": "cubic-bezier(0.22, 1, 0.36, 1)", "type": "cubicBezier" },
      "hover":   { "value": "cubic-bezier(0.16, 1, 0.3, 1)",  "type": "cubicBezier" },
      "in":      { "value": "cubic-bezier(0.4, 0.0, 1, 1)",   "type": "cubicBezier" },
      "out":     { "value": "cubic-bezier(0.0, 0.0, 0.2, 1)", "type": "cubicBezier" },
      "spring":  { "value": "cubic-bezier(0.34, 1.56, 0.64, 1)", "type": "cubicBezier" }
    }
  },
  "zIndex": {
    "below":    { "value": "-1",   "type": "zIndex" },
    "base":     { "value": "0",    "type": "zIndex" },
    "raised":   { "value": "10",   "type": "zIndex" },
    "dropdown": { "value": "1000", "type": "zIndex" },
    "sticky":   { "value": "1100", "type": "zIndex" },
    "overlay":  { "value": "1200", "type": "zIndex" },
    "modal":    { "value": "1300", "type": "zIndex" },
    "popover":  { "value": "1400", "type": "zIndex" },
    "toast":    { "value": "1500", "type": "zIndex" },
    "top":      { "value": "1600", "type": "zIndex" }
  },
  "container": {
    "max": { "value": "1280px", "type": "sizing", "kemet": "container.xl" }
  }
}
